QPE/Backend.py
QPE/ExperimentRunner.py
QPE/HelpFunctions.py
QPE/Iterative.py
QPE/Kitaev.py
QPE/PhaseEstimator.py
QPE/QFT.py
QPE/Unitary.py
QPE/UnpackData.py
QPE/__init__.py
QPE-0.0.2.dist-info/LICENSE
QPE-0.0.2.dist-info/METADATA
QPE-0.0.2.dist-info/WHEEL
QPE-0.0.2.dist-info/top_level.txt
QPE-0.0.2.dist-info/RECORD
