Metadata-Version: 2.1
Name: QPE
Version: 0.0.2
Summary: Qiskit applications for Quantum Phase Estimationn
Home-page: https://github.com/hjaleta/QPE
Author: Hjalmar Lindstedt, Riccardo Conte, Miguel Carrera Belo
Author-email: hjaleta@gmail.com
License: : OSI Approved :: MIT License
Platform: UNKNOWN
License-File: LICENSE
Requires-Dist: numpy
Requires-Dist: qiskit
Requires-Dist: quantuminspire
